badwolf/__init__.py
badwolf/app.py
badwolf/artifacts.py
badwolf/bitbucket.py
badwolf/builder.py
badwolf/cli.py
badwolf/cloner.py
badwolf/context.py
badwolf/default_settings.py
badwolf/exceptions.py
badwolf/extensions.py
badwolf/notification.py
badwolf/pipeline.py
badwolf/security.py
badwolf/spec.py
badwolf/tasks.py
badwolf/utils.py
badwolf/wsgi.py
badwolf/deploy/__init__.py
badwolf/deploy/providers/__init__.py
badwolf/deploy/providers/pypi.py
badwolf/deploy/providers/script.py
badwolf/lint/__init__.py
badwolf/lint/processor.py
badwolf/lint/utils.py
badwolf/lint/linters/__init__.py
badwolf/lint/linters/bandit.py
badwolf/lint/linters/csslint.py
badwolf/lint/linters/eslint.py
badwolf/lint/linters/flake8.py
badwolf/lint/linters/hadolint.py
badwolf/lint/linters/jsonlint.py
badwolf/lint/linters/mypy.py
badwolf/lint/linters/pycodestyle.py
badwolf/lint/linters/pylint.py
badwolf/lint/linters/rstlint.py
badwolf/lint/linters/sasslint.py
badwolf/lint/linters/shellcheck.py
badwolf/lint/linters/stylelint.py
badwolf/lint/linters/yamllint.py
badwolf/log/__init__.py
badwolf/log/views.py
badwolf/oauth/__init__.py
badwolf/oauth/views.py
badwolf/templates/script.sh
badwolf/templates/mail/test_failure.html
badwolf/templates/mail/test_success.html
badwolf/webhook/__init__.py
badwolf/webhook/views.py
badwolf-0.15.0.dist-info/LICENSE
badwolf-0.15.0.dist-info/METADATA
badwolf-0.15.0.dist-info/WHEEL
badwolf-0.15.0.dist-info/entry_points.txt
badwolf-0.15.0.dist-info/top_level.txt
badwolf-0.15.0.dist-info/RECORD
