Metadata-Version: 2.1
Name: badwolf
Version: 0.15.0
Summary: Docker based continuous integration and code lint review system for BitBucket
Home-page: UNKNOWN
Author: messense
Author-email: messense@icloud.com
License: UNKNOWN
Keywords: ci,bitbucket
Platform: UNKNOWN
Requires-Dist: Flask (>=0.11)
Requires-Dist: click (>=6.2)
Requires-Dist: docker (>=2.0.2)
Requires-Dist: GitPython (>=1.0.1)
Requires-Dist: raven (>=5.10.2)
Requires-Dist: blinker (>=1.4)
Requires-Dist: pyyaml (>=3.11)
Requires-Dist: flask-mail (>=0.9.1)
Requires-Dist: unidiff (>=0.5.2)
Requires-Dist: optionaldict (>=0.1.1)
Requires-Dist: flake8 (>=3.0.0)
Requires-Dist: pep8-naming (>=0.3.3)
Requires-Dist: pycodestyle
Requires-Dist: yamllint (>=1.0.0)
Requires-Dist: bandit (>=0.17.3)
Requires-Dist: restructuredtext-lint (>=0.14.2)
Requires-Dist: pylint (>=1.5.4)
Requires-Dist: certifi
Requires-Dist: requests[security]
Requires-Dist: flake8-import-order (>=0.16)
Requires-Dist: deansi (>=1.2)
Requires-Dist: cryptography (>=1.7.1)
Requires-Dist: marshmallow (<4.0.0,>=3.0.0rc6)
Requires-Dist: marshmallow-oneofschema (>=1.0.5)
Requires-Dist: twine
Requires-Dist: flake8-bugbear
Requires-Dist: is-minified-js (>=0.3.0)
Requires-Dist: mypy
Requires-Dist: flake8-network-timeout
Requires-Dist: flake8-comprehensions
Requires-Dist: hvac[parser]
